sxd_sdk/__init__.py
sxd_sdk/client.py
sxd_sdk/docker.py
sxd_sdk/pipeline.py
sxd_sdk/scaffold.py
sxd_sdk/schemas.py
sxd_sdk/testing.py
sxd_sdk-0.1.0.dist-info/METADATA
sxd_sdk-0.1.0.dist-info/WHEEL
sxd_sdk-0.1.0.dist-info/licenses/LICENSE
sxd_sdk-0.1.0.dist-info/RECORD
