Metadata-Version: 2.4
Name: sxd-sdk
Version: 0.1.0
Summary: SDK for building and deploying data pipelines on SentientX Data Platform
Project-URL: Homepage, https://github.com/sentient-x/sxd
Project-URL: Documentation, https://sentient-x.github.io/sxd
Project-URL: Repository, https://github.com/sentient-x/sxd
Project-URL: Issues, https://github.com/sentient-x/sxd/issues
Author-email: SentientX <dev@sentient-x.com>
License: Apache-2.0
License-File: LICENSE
Keywords: computer-vision,data-pipelines,distributed-computing,machine-learning,temporal,workflows
Classifier: Development Status :: 4 - Beta
Classifier: Intended Audience :: Developers
Classifier: License :: OSI Approved :: Apache Software License
Classifier: Operating System :: OS Independent
Classifier: Programming Language :: Python :: 3
Classifier: Programming Language :: Python :: 3.11
Classifier: Programming Language :: Python :: 3.12
Classifier: Topic :: Scientific/Engineering :: Artificial Intelligence
Classifier: Topic :: System :: Distributed Computing
Requires-Python: >=3.11
Requires-Dist: httpx>=0.23.0
Requires-Dist: pydantic>=2.0.0
Requires-Dist: temporalio>=1.5.0
Provides-Extra: all
Requires-Dist: mypy>=1.8.0; extra == 'all'
Requires-Dist: numpy>=1.24.0; extra == 'all'
Requires-Dist: opencv-python>=4.8.0; extra == 'all'
Requires-Dist: pytest-asyncio>=0.23.0; extra == 'all'
Requires-Dist: pytest-cov>=4.1.0; extra == 'all'
Requires-Dist: pytest>=8.0.0; extra == 'all'
Requires-Dist: ruff>=0.2.0; extra == 'all'
Requires-Dist: torch>=2.0.0; extra == 'all'
Requires-Dist: torchvision>=0.15.0; extra == 'all'
Provides-Extra: dev
Requires-Dist: mypy>=1.8.0; extra == 'dev'
Requires-Dist: pytest-asyncio>=0.23.0; extra == 'dev'
Requires-Dist: pytest-cov>=4.1.0; extra == 'dev'
Requires-Dist: pytest>=8.0.0; extra == 'dev'
Requires-Dist: ruff>=0.2.0; extra == 'dev'
Provides-Extra: opencv
Requires-Dist: numpy>=1.24.0; extra == 'opencv'
Requires-Dist: opencv-python>=4.8.0; extra == 'opencv'
Provides-Extra: pytorch
Requires-Dist: torch>=2.0.0; extra == 'pytorch'
Requires-Dist: torchvision>=0.15.0; extra == 'pytorch'
